<?xml version="1.0" encoding="utf-8" ?><dwsync><file name="AvenirLTStd-Book.261879f.ttf" server="ftp.huestudios.com/sites/philharmonic/" local="3587755853" remote="3587745240" Dst="-1" /><file name="AvenirLTStd-Book.ad2fa12.woff2" server="ftp.huestudios.com/sites/philharmonic/" local="3587755853" remote="3587745240" Dst="-1" /><file name="AvenirLTStd-Book.a8f6e12.eot" server="ftp.huestudios.com/sites/philharmonic/" local="3587755853" remote="3587745240" Dst="-1" /><file name="AvenirLTStd-Book.c151a2d.woff" server="ftp.huestudios.com/sites/philharmonic/" local="3587755853" remote="3587745240" Dst="-1" /><file name="DINPro-CondensedLight.b90ad56.woff" server="ftp.huestudios.com/sites/philharmonic/" local="3587755853" remote="3587745240" Dst="-1" /><file name="DINPro-CondensedLight.7aeeb3c.woff2" server="ftp.huestudios.com/sites/philharmonic/" local="3587755853" remote="3587745240" Dst="-1" /><file name="DINPro-CondensedLight.eabd6e1.eot" server="ftp.huestudios.com/sites/philharmonic/" local="3587755853" remote="3587745240" Dst="-1" /><file name="DINPro-CondensedLight.f03e1cc.ttf" server="ftp.huestudios.com/sites/philharmonic/" local="3587755853" remote="3587745240" Dst="-1" /><file name="Framework7Icons-Regular.9900d2b.ttf" server="ftp.huestudios.com/sites/philharmonic/" local="3587755853" remote="3587745240" Dst="-1" /><file name="Framework7Icons-Regular.bb6aae4.eot" server="ftp.huestudios.com/sites/philharmonic/" local="3587755853" remote="3587745240" Dst="-1" /><file name="Framework7Icons-Regular.eb7a418.woff" server="ftp.huestudios.com/sites/philharmonic/" local="3587755853" remote="3587745240" Dst="-1" /><file name="Framework7Icons-Regular.f3e1eae.woff2" server="ftp.huestudios.com/sites/philharmonic/" local="3587755853" remote="3587745240" Dst="-1" /></dwsync>